Metadata-Version: 2.1
Name: drf-keyed-list-bihealth
Version: 0.1.1
Summary: Fork of drf-keyed-list maintained by @bihealth
Home-page: http://github.com/bihealth/drf-keyed-list
Author: Manuel Holtgrewe, Mikko Nieminen, Oliver Stolpe
Author-email: manuel.holtgrewe@bih-charite.de, mikko.nieminen@bih-charite.de, oliver.stolpe@bih-charite.de
License: Apache 2.0
Keywords: drf restframework rest_framework django_rest_framework serializers drf_mapped_nested
Classifier: Development Status :: 3 - Alpha
Classifier: Environment :: Web Environment
Classifier: Framework :: Django
Classifier: Framework :: Django :: 3.0
Classifier: Framework :: Django :: 4.0
Classifier: Intended Audience :: Developers
Classifier: License :: OSI Approved :: Apache Software License
Classifier: Operating System :: OS Independent
Classifier: Programming Language :: Python
Classifier: Programming Language :: Python :: 3
Classifier: Programming Language :: Python :: 3.8
Classifier: Programming Language :: Python :: 3.9
Classifier: Programming Language :: Python :: 3.10
Classifier: Programming Language :: Python :: 3.11
Classifier: Topic :: Internet :: WWW/HTTP
License-File: LICENSE.md
